{"@type":"TypesConfig","types":[
    {"@type":"TypeConfig","name":"metadata","class":"com.draagon.meta.MetaData","children":[
        {"@type":"ChildConfig","type":"object","subType":"*","name":"*"},
        {"@type":"ChildConfig","type":"field","subType":"*","name":"*"},
        {"@type":"ChildConfig","type":"validator","subType":"*","name":"*"}],
        "subTypes":[]
    },
    {"@type":"TypeConfig","name":"attr","class":"com.draagon.meta.attr.MetaAttribute","defaultSubType":"string","children":[],"subTypes":[
        {"@type":"SubTypeConfig","name":"string","class":"com.draagon.meta.attr.StringAttribute","children":[]},
        {"@type":"SubTypeConfig","name":"stringArray","class":"com.draagon.meta.attr.StringArrayAttribute","children":[]},
        {"@type":"SubTypeConfig","name":"properties","class":"com.draagon.meta.attr.PropertiesAttribute","children":[]},
        {"@type":"SubTypeConfig","name":"class","class":"com.draagon.meta.attr.ClassAttribute","children":[]},
        {"@type":"SubTypeConfig","name":"boolean","class":"com.draagon.meta.attr.BooleanAttribute","children":[]},
        {"@type":"SubTypeConfig","name":"int","class":"com.draagon.meta.attr.IntAttribute","children":[]}]
    },
    {"@type":"TypeConfig","name":"object","class":"com.draagon.meta.object.MetaObject","defaultSubType":"map","children":[
        {"@type":"ChildConfig","type":"attr","subType":"boolean","name":"_isAbstract"},
        {"@type":"ChildConfig","type":"attr","subType":"boolean","name":"isInterface"},
        {"@type":"ChildConfig","type":"key","subType":"primary","name":"primary"},
        {"@type":"ChildConfig","type":"key","subType":"secondary","name":"*"},
        {"@type":"ChildConfig","type":"key","subType":"foreign","name":"*"},
        {"@type":"ChildConfig","type":"field","subType":"*","name":"*"}],
        "subTypes":[
            {"@type":"SubTypeConfig","name":"pojo","class":"com.draagon.meta.object.pojo.PojoMetaObject","children":[
                {"@type":"ChildConfig","type":"attr","subType":"string","name":"object"}]
            },
            {"@type":"SubTypeConfig","name":"map","class":"com.draagon.meta.object.mapped.MappedMetaObject","children":[
                {"@type":"ChildConfig","type":"attr","subType":"string","name":"object"}]
            },
            {"@type":"SubTypeConfig","name":"proxy","class":"com.draagon.meta.object.proxy.ProxyMetaObject","children":[
                {"@type":"ChildConfig","type":"attr","subType":"string","name":"object"},
                {"@type":"ChildConfig","type":"attr","subType":"string","name":"proxyObject"}]
            }]
        },
        {"@type":"TypeConfig","name":"key","class":"com.draagon.meta.key.MetaKey","defaultSubType":"primary","children":[
            {"@type":"ChildConfig","type":"attr","subType":"stringArray","name":"keys"}],
            "subTypes":[
                {"@type":"SubTypeConfig","name":"primary","class":"com.draagon.meta.key.PrimaryKey","children":[]},
                {"@type":"SubTypeConfig","name":"secondary","class":"com.draagon.meta.key.SecondaryKey","children":[]},
                {"@type":"SubTypeConfig","name":"foreign","class":"com.draagon.meta.key.ForeignKey","children":[
                    {"@type":"ChildConfig","type":"attr","subType":"string","name":"foreignObjectRef"},
                    {"@type":"ChildConfig","type":"attr","subType":"string","name":"foreignKey"}]
                }]
        },
        {"@type":"TypeConfig","name":"field","class":"com.draagon.meta.field.MetaField","defaultSubType":"string","children":[
            {"@type":"ChildConfig","type":"attr","subType":"boolean","name":"_isAbstract"},
            {"@type":"ChildConfig","type":"attr","subType":"stringArray","name":"validation"},
            {"@type":"ChildConfig","type":"attr","subType":"string","name":"defaultValue"},
            {"@type":"ChildConfig","type":"validator","subType":"*","name":"*"}],
            "subTypes":[
                {"@type":"SubTypeConfig","name":"boolean","class":"com.draagon.meta.field.BooleanField","children":[]},
                {"@type":"SubTypeConfig","name":"byte","class":"com.draagon.meta.field.ByteField","children":[]},
                {"@type":"SubTypeConfig","name":"short","class":"com.draagon.meta.field.ShortField","children":[]},
                {"@type":"SubTypeConfig","name":"int","class":"com.draagon.meta.field.IntegerField","children":[]},
                {"@type":"SubTypeConfig","name":"long","class":"com.draagon.meta.field.LongField","children":[]},
                {"@type":"SubTypeConfig","name":"float","class":"com.draagon.meta.field.FloatField","children":[]},
                {"@type":"SubTypeConfig","name":"double","class":"com.draagon.meta.field.DoubleField","children":[]},
                {"@type":"SubTypeConfig","name":"string","class":"com.draagon.meta.field.StringField","children":[]},
                {"@type":"SubTypeConfig","name":"date","class":"com.draagon.meta.field.DateField","children":[]},
                {"@type":"SubTypeConfig","name":"class","class":"com.draagon.meta.field.ClassField","children":[]},
                {"@type":"SubTypeConfig","name":"stringArray","class":"com.draagon.meta.field.StringArrayField","children":[]},
                {"@type":"SubTypeConfig","name":"object","class":"com.draagon.meta.field.ObjectField","children":[
                    {"@type":"ChildConfig","type":"attr","subType":"string","name":"objectRef"}]
                },
                {"@type":"SubTypeConfig","name":"objectArray","class":"com.draagon.meta.field.ObjectArrayField","children":[
                    {"@type":"ChildConfig","type":"attr","subType":"string","name":"objectRef"}]
                }]
        },
        {"@type":"TypeConfig","name":"validator","class":"com.draagon.meta.validator.MetaValidator","defaultSubType":"required","defaultNamePrefix":"validator","children":[],"subTypes":[
            {"@type":"SubTypeConfig","name":"required","class":"com.draagon.meta.validator.RequiredValidator","children":[]},
            {"@type":"SubTypeConfig","name":"regex","class":"com.draagon.meta.validator.RegexValidator","children":[
                {"@type":"ChildConfig","type":"attr","subType":"string","name":"mask"}]
            },
            {"@type":"SubTypeConfig","name":"numeric","class":"com.draagon.meta.validator.NumericValidator","children":[]},
            {"@type":"SubTypeConfig","name":"length","class":"com.draagon.meta.validator.LengthValidator","children":[
                {"@type":"ChildConfig","type":"attr","subType":"int","name":"min"},
                {"@type":"ChildConfig","type":"attr","subType":"int","name":"max"}]
            },
            {"@type":"SubTypeConfig","name":"array","class":"com.draagon.meta.validator.ArrayValidator","children":[
                {"@type":"ChildConfig","type":"attr","subType":"int","name":"minSize"},
                {"@type":"ChildConfig","type":"attr","subType":"int","name":"maxSize"}]
            }]
        }]
}
